blocksim_quadcopter/AttPilot.py
blocksim_quadcopter/Motor.py
blocksim_quadcopter/Quadri.py
blocksim_quadcopter/VTOLPilot.py
blocksim_quadcopter/__init__.py
blocksim_quadcopter/constants.py
blocksim_quadcopter/exceptions.py
blocksim_quadcopter-0.2.1.dist-info/AUTHORS.rst
blocksim_quadcopter-0.2.1.dist-info/LICENSE
blocksim_quadcopter-0.2.1.dist-info/METADATA
blocksim_quadcopter-0.2.1.dist-info/WHEEL
blocksim_quadcopter-0.2.1.dist-info/top_level.txt
blocksim_quadcopter-0.2.1.dist-info/RECORD
