Metadata-Version: 2.1
Name: blocksim-quadcopter
Version: 0.2.1
Summary: A set of computers to simulate a quadcopter
Home-page: https://gitlab.com/manawenuz/blocksim_quadcopter
Author: John Gray
Author-email: manawenuz@johncloud.fr
License: UNKNOWN
Platform: any
Classifier: Development Status :: 3 - Alpha
Classifier: Intended Audience :: Developers
Classifier: License :: OSI Approved :: MIT License
Classifier: Operating System :: OS Independent
Classifier: Programming Language :: Python
Classifier: Programming Language :: Python :: 3.6
Classifier: Topic :: Software Development :: Libraries :: Python Modules
Requires-Python: >=3.6
License-File: LICENSE
License-File: AUTHORS.rst
Requires-Dist: numpy
Requires-Dist: scipy
Requires-Dist: matplotlib
Requires-Dist: blocksim
